agent_framework_purview/__init__.py
agent_framework_purview/_cache.py
agent_framework_purview/_client.py
agent_framework_purview/_exceptions.py
agent_framework_purview/_middleware.py
agent_framework_purview/_models.py
agent_framework_purview/_processor.py
agent_framework_purview/_settings.py
agent_framework_purview-1.0.0b260130.dist-info/licenses/LICENSE
agent_framework_purview-1.0.0b260130.dist-info/WHEEL
agent_framework_purview-1.0.0b260130.dist-info/METADATA
agent_framework_purview-1.0.0b260130.dist-info/RECORD
