Metadata-Version: 2.4
Name: agent-framework-purview
Version: 1.0.0b260130
Summary: Microsoft Purview (Graph dataSecurityAndGovernance) integration for Microsoft Agent Framework.
Author-email: Microsoft <af-support@microsoft.com>
Requires-Python: >=3.10
Classifier: License :: OSI Approved :: MIT License
Classifier: Development Status :: 3 - Alpha
Classifier: Intended Audience :: Developers
Classifier: Programming Language :: Python :: 3
Classifier: Programming Language :: Python :: 3.10
Classifier: Programming Language :: Python :: 3.11
Classifier: Programming Language :: Python :: 3.12
Classifier: Programming Language :: Python :: 3.13
Classifier: Programming Language :: Python :: 3.14
Classifier: Framework :: Pydantic :: 2
Classifier: Typing :: Typed
License-File: LICENSE
Requires-Dist: agent-framework-core
Requires-Dist: azure-core>=1.30.0
Requires-Dist: httpx>=0.27.0
Project-URL: homepage, https://github.com/microsoft/agent-framework
Project-URL: issues, https://github.com/microsoft/agent-framework/issues
Project-URL: release_notes, https://github.com/microsoft/agent-framework/releases
Project-URL: source, https://github.com/microsoft/agent-framework/tree/main/python
